[
  {
    "title": "빛고을배드민턴클럽의 첫 번째 공지",
    "description": "빛고을 배드민턴 클럽은 정말 대단해 정말 최고야 정말 멋져 정말 대단해",
    "notionLink": "c39a455b98ef402fbb25b1c935b35dd3",
    "date": "2024-05-21",
    "id": 0
  },
  {
    "title": "빛고을배드민턴클럽의 첫 번째 공지",
    "description": "빛고을 배드민턴 클럽은 정말 대단해 정말 최고야 정말 멋져 정말 대단해",
    "notionLink": "c39a455b98ef402fbb25b1c935b35dd3",
    "date": "2024-05-21",
    "id": 1
  },
  {
    "title": "빛고을배드민턴클럽의 첫 번째 공지",
    "description": "빛고을 배드민턴 클럽은 정말 대단해 정말 최고야 정말 멋져 정말 대단해",
    "notionLink": "c39a455b98ef402fbb25b1c935b35dd3",
    "date": "2024-05-21",
    "id": 2
  }
]
